<annotation>
	<folder></folder>
	<filename>01FV9YVA3DVS08VQHFWHM2MPS3_jpeg.rf.7bcc9c9b3887d4cd9b358e04fc6f0bf5.jpg</filename>
	<path>01FV9YVA3DVS08VQHFWHM2MPS3_jpeg.rf.7bcc9c9b3887d4cd9b358e04fc6f0bf5.jpg</path>
	<source>
		<database>roboflow.com</database>
	</source>
	<size>
		<width>416</width>
		<height>416</height>
		<depth>3</depth>
	</size>
	<segmented>0</segmented>
	<object>
		<name>pinky</name>
		<pose>Unspecified</pose>
		<truncated>0</truncated>
		<difficult>0</difficult>
		<occluded>0</occluded>
		<bndbox>
			<xmin>333</xmin>
			<xmax>341</xmax>
			<ymin>225</ymin>
			<ymax>230</ymax>
		</bndbox>
	</object>
	<object>
		<name>pinky</name>
		<pose>Unspecified</pose>
		<truncated>0</truncated>
		<difficult>0</difficult>
		<occluded>0</occluded>
		<bndbox>
			<xmin>295</xmin>
			<xmax>304</xmax>
			<ymin>79</ymin>
			<ymax>86</ymax>
		</bndbox>
	</object>
	<object>
		<name>left_foot</name>
		<pose>Unspecified</pose>
		<truncated>0</truncated>
		<difficult>0</difficult>
		<occluded>0</occluded>
		<bndbox>
			<xmin>30</xmin>
			<xmax>363</xmax>
			<ymin>59</ymin>
			<ymax>217</ymax>
		</bndbox>
	</object>
	<object>
		<name>right_foot</name>
		<pose>Unspecified</pose>
		<truncated>0</truncated>
		<difficult>0</difficult>
		<occluded>0</occluded>
		<bndbox>
			<xmin>41</xmin>
			<xmax>392</xmax>
			<ymin>147</ymin>
			<ymax>306</ymax>
		</bndbox>
	</object>
	<object>
		<name>ankle</name>
		<pose>Unspecified</pose>
		<truncated>0</truncated>
		<difficult>0</difficult>
		<occluded>0</occluded>
		<bndbox>
			<xmin>102</xmin>
			<xmax>109</xmax>
			<ymin>192</ymin>
			<ymax>197</ymax>
		</bndbox>
	</object>
	<object>
		<name>ankle</name>
		<pose>Unspecified</pose>
		<truncated>0</truncated>
		<difficult>0</difficult>
		<occluded>0</occluded>
		<bndbox>
			<xmin>106</xmin>
			<xmax>113</xmax>
			<ymin>212</ymin>
			<ymax>217</ymax>
		</bndbox>
	</object>
	<object>
		<name>heel</name>
		<pose>Unspecified</pose>
		<truncated>0</truncated>
		<difficult>0</difficult>
		<occluded>0</occluded>
		<bndbox>
			<xmin>58</xmin>
			<xmax>66</xmax>
			<ymin>227</ymin>
			<ymax>232</ymax>
		</bndbox>
	</object>
	<object>
		<name>heel</name>
		<pose>Unspecified</pose>
		<truncated>0</truncated>
		<difficult>0</difficult>
		<occluded>0</occluded>
		<bndbox>
			<xmin>53</xmin>
			<xmax>59</xmax>
			<ymin>207</ymin>
			<ymax>212</ymax>
		</bndbox>
	</object>
	<object>
		<name>toe</name>
		<pose>Unspecified</pose>
		<truncated>0</truncated>
		<difficult>0</difficult>
		<occluded>0</occluded>
		<bndbox>
			<xmin>340</xmin>
			<xmax>349</xmax>
			<ymin>162</ymin>
			<ymax>170</ymax>
		</bndbox>
	</object>
	<object>
		<name>toe</name>
		<pose>Unspecified</pose>
		<truncated>0</truncated>
		<difficult>0</difficult>
		<occluded>0</occluded>
		<bndbox>
			<xmin>326</xmin>
			<xmax>333</xmax>
			<ymin>132</ymin>
			<ymax>137</ymax>
		</bndbox>
	</object>
</annotation>
